sinapsis_elevenlabs/src/sinapsis_elevenlabs/__init__.py
sinapsis_elevenlabs/src/sinapsis_elevenlabs/helpers/__init__.py
sinapsis_elevenlabs/src/sinapsis_elevenlabs/helpers/env_var_keys.py
sinapsis_elevenlabs/src/sinapsis_elevenlabs/helpers/tags.py
sinapsis_elevenlabs/src/sinapsis_elevenlabs/helpers/voice_utils.py
sinapsis_elevenlabs/src/sinapsis_elevenlabs/templates/__init__.py
sinapsis_elevenlabs/src/sinapsis_elevenlabs/templates/elevenlabs_base.py
sinapsis_elevenlabs/src/sinapsis_elevenlabs/templates/elevenlabs_sts.py
sinapsis_elevenlabs/src/sinapsis_elevenlabs/templates/elevenlabs_tts.py
sinapsis_elevenlabs/src/sinapsis_elevenlabs/templates/elevenlabs_voice_clone.py
sinapsis_elevenlabs/src/sinapsis_elevenlabs/templates/elevenlabs_voice_generation.py
sinapsis_f5_tts/src/sinapsis_f5_tts/__init__.py
sinapsis_f5_tts/src/sinapsis_f5_tts/helpers/__init__.py
sinapsis_f5_tts/src/sinapsis_f5_tts/helpers/tags.py
sinapsis_f5_tts/src/sinapsis_f5_tts/templates/__init__.py
sinapsis_f5_tts/src/sinapsis_f5_tts/templates/f5_tts_inference.py
sinapsis_kokoro/src/sinapsis_kokoro/__init__.py
sinapsis_kokoro/src/sinapsis_kokoro/helpers/kokoro_utils.py
sinapsis_kokoro/src/sinapsis_kokoro/helpers/tags.py
sinapsis_kokoro/src/sinapsis_kokoro/templates/__init__.py
sinapsis_kokoro/src/sinapsis_kokoro/templates/kokoro_tts.py
sinapsis_orpheus_cpp/src/sinapsis_orpheus_cpp/__init__.py
sinapsis_orpheus_cpp/src/sinapsis_orpheus_cpp/helpers/__init__.py
sinapsis_orpheus_cpp/src/sinapsis_orpheus_cpp/helpers/tags.py
sinapsis_orpheus_cpp/src/sinapsis_orpheus_cpp/templates/__init__.py
sinapsis_orpheus_cpp/src/sinapsis_orpheus_cpp/templates/orpheus_tts.py
sinapsis_orpheus_cpp/src/sinapsis_orpheus_cpp/thirdparty/helpers.py
sinapsis_parakeet_tdt/src/sinapsis_parakeet_tdt/__init__.py
sinapsis_parakeet_tdt/src/sinapsis_parakeet_tdt/helpers/__init__.py
sinapsis_parakeet_tdt/src/sinapsis_parakeet_tdt/helpers/tags.py
sinapsis_parakeet_tdt/src/sinapsis_parakeet_tdt/templates/__init__.py
sinapsis_speech-0.4.5.dist-info/licenses/LICENSE
sinapsis_speech-0.4.5.dist-info/METADATA
sinapsis_speech-0.4.5.dist-info/WHEEL
sinapsis_speech-0.4.5.dist-info/top_level.txt
sinapsis_speech-0.4.5.dist-info/RECORD
