Metadata-Version: 2.4
Name: sinapsis-speech
Version: 0.4.5
Summary: Generate speech using various libraries.
Author-email: SinapsisAI <dev@sinapsis.tech>
Project-URL: Homepage, https://sinapsis.tech
Project-URL: Documentation, https://docs.sinapsis.tech/docs/sinapsis-speech
Project-URL: Tutorials, https://docs.sinapsis.tech/tutorials
Project-URL: Repository, https://github.com/Sinapsis-AI/sinapsis-speech.git
Requires-Python: >=3.10
License-File: LICENSE
Requires-Dist: pip>=24.3.1
Requires-Dist: sinapsis>=0.2.2
Provides-Extra: all
Requires-Dist: sinapsis-elevenlabs[all]; extra == "all"
Requires-Dist: sinapsis-f5-tts[all]; extra == "all"
Requires-Dist: sinapsis-kokoro[all]; extra == "all"
Requires-Dist: sinapsis-speech[gradio-app]; extra == "all"
Requires-Dist: sinapsis-zonos[all]; extra == "all"
Requires-Dist: sinapsis-parakeet-tdt[all]; extra == "all"
Requires-Dist: sinapsis-orpheus-cpp[all]; extra == "all"
Provides-Extra: gradio-app
Requires-Dist: sinapsis[webapp]>=0.2.3; extra == "gradio-app"
Dynamic: license-file
